htmlst/HTMLSentenceTokenizer.py
htmlst-0.1.0b1.dist-info/DESCRIPTION.rst
htmlst-0.1.0b1.dist-info/METADATA
htmlst-0.1.0b1.dist-info/RECORD
htmlst-0.1.0b1.dist-info/WHEEL
htmlst-0.1.0b1.dist-info/metadata.json
htmlst-0.1.0b1.dist-info/top_level.txt
