Metadata-Version: 2.0
Name: htmlst
Version: 0.1.0b1
Summary: An API which extracts sentences from HTML
Home-page: https://github.com/wardbradt/HTMLST
Author: Ward Bradt
Author-email: UNKNOWN
License: UNKNOWN
Keywords: nlp machinelearning development
Platform: UNKNOWN
Requires-Dist: html5lib
Requires-Dist: nltk
